tests/__init__.py
tests/test_setting_reload.py
tests/test_uid.py
yzcore/__init__.py
yzcore/__main__.py
yzcore/decorators.py
yzcore/default_settings.py
yzcore/exceptions.py
yzcore/core/__init__.py
yzcore/core/const.py
yzcore/core/data_hash.py
yzcore/core/datastructures.py
yzcore/core/encoders.py
yzcore/core/management/__init__.py
yzcore/core/management/base.py
yzcore/core/management/templates.py
yzcore/core/management/commands/__init__.py
yzcore/core/management/commands/startapp.py
yzcore/core/management/commands/startproject.py
yzcore/db/__init__.py
yzcore/db/db_session.py
yzcore/db/pymongo_crud_base.py
yzcore/db/sqlalchemy_crud_base.py
yzcore/extensions/__init__.py
yzcore/extensions/aliyun_oss.py
yzcore/extensions/uid.py
yzcore/extensions/oss/__init__.py
yzcore/extensions/oss/aliyun.py
yzcore/extensions/oss/amazon.py
yzcore/extensions/oss/huawei.py
yzcore/logger/__init__.py
yzcore/logger/config.py
yzcore/logger/filters.py
yzcore/logger/handlers.py
yzcore/request/__init__.py
yzcore/request/aio_http.py
yzcore/response/__init__.py
yzcore/response/response.py
yzcore/response/response_code.py
yzcore/templates/__init__.py
yzcore/templates/app_template/__init__.py
yzcore/templates/app_template/controllers.py
yzcore/templates/app_template/models.py
yzcore/templates/app_template/schemas.py
yzcore/templates/app_template/tests.py
yzcore/templates/app_template/views.py
yzcore/templates/project_template/.gitignore
yzcore/templates/project_template/README.md
yzcore/templates/project_template/requirements.txt
yzcore/templates/project_template/docs/install_explain.md
yzcore/templates/project_template/docs/supervisor.ini
yzcore/templates/project_template/migrations/README.md
yzcore/templates/project_template/src/__init__.py
yzcore/templates/project_template/src/main.py
yzcore/templates/project_template/src/settings.py
yzcore/templates/project_template/src/apps/__init__.py
yzcore/templates/project_template/src/conf/config_dev.ini
yz_core-0.2.1.dist-info/LICENSE
yz_core-0.2.1.dist-info/METADATA
yz_core-0.2.1.dist-info/WHEEL
yz_core-0.2.1.dist-info/entry_points.txt
yz_core-0.2.1.dist-info/top_level.txt
yz_core-0.2.1.dist-info/RECORD
