Metadata-Version: 2.1
Name: yz-core
Version: 0.2.1
Summary: An ID generator for distributed microservices
Home-page: https://github.com/lixuemin13/yz-core.git
Author: lxm
Author-email: luoyuren13@gmail.com
License: UNKNOWN
Platform: UNKNOWN
Classifier: Programming Language :: Python :: 3
Classifier: License :: OSI Approved :: MIT License
Classifier: Operating System :: OS Independent
Requires-Python: >=3.6.8
License-File: LICENSE
Requires-Dist: fastapi (>=0.68.1)
Requires-Dist: uvicorn (>0.13)
Requires-Dist: yzrpc (>=0.1)
Provides-Extra: oss-aliyun
Requires-Dist: oss2 (!=3.0.0,>=2.13.0) ; extra == 'oss-aliyun'
Provides-Extra: oss-aws
Requires-Dist: boto3 (==1.17.27) ; extra == 'oss-aws'
Provides-Extra: oss-huawei
Requires-Dist: esdk-obs-python (==3.20.11) ; extra == 'oss-huawei'
Provides-Extra: rpc
Requires-Dist: yzrpc (>=0.1) ; extra == 'rpc'
